brickblock/__init__.py
brickblock/index.py
brickblock/objects.py
brickblock/space.py
brickblock/temp-space.py
brickblock/visualisation.py
brickblock-0.2.5.dist-info/LICENSE
brickblock-0.2.5.dist-info/WHEEL
brickblock-0.2.5.dist-info/METADATA
brickblock-0.2.5.dist-info/RECORD
