Metadata-Version: 2.1
Name: brickblock
Version: 0.2.5
Summary: A fun visualisation library for those that like boxes
Home-page: https://github.com/danielsoutar/brickblock
Author: Daniel Soutar
Author-email: danielsoutar144@gmail.com
Requires-Python: >=3.9,<4.0
Classifier: Programming Language :: Python :: 3
Classifier: Programming Language :: Python :: 3.9
Classifier: Programming Language :: Python :: 3.10
Classifier: Programming Language :: Python :: 3.11
Requires-Dist: matplotlib (>=3.7.2,<4.0.0)
Requires-Dist: numpy (>=1.25.1,<2.0.0)
Requires-Dist: pytest (>=7.4.0,<8.0.0)
Project-URL: Repository, https://github.com/danielsoutar/brickblock
